backup_helper/__init__.py
backup_helper/__main__.py
backup_helper/backup_helper.py
backup_helper/cli.py
backup_helper/disk_work_queue.py
backup_helper/exceptions.py
backup_helper/helpers.py
backup_helper/interactive.py
backup_helper/py.typed
backup_helper/source.py
backup_helper/target.py
backup_helper/work.py
backup_helper-0.3.0.dist-info/METADATA
backup_helper-0.3.0.dist-info/WHEEL
backup_helper-0.3.0.dist-info/entry_points.txt
backup_helper-0.3.0.dist-info/top_level.txt
backup_helper-0.3.0.dist-info/RECORD
