Metadata-Version: 2.4
Name: backup-helper
Version: 0.3.0
Summary: Helper tool for creating plain-file cold-storage archives including checksum files
Author-email: omgitsmoe <60219950+omgitsmoe@users.noreply.github.com>
Project-URL: Homepage, https://github.com/omgitsmoe/backup_helper
Project-URL: Bug Tracker, https://github.com/omgitsmoe/backup_helper/issues
Keywords: script,verify,backup,archival,bit-rot
Classifier: Programming Language :: Python :: 3
Classifier: License :: OSI Approved :: MIT License
Classifier: Operating System :: OS Independent
Requires-Python: >=3.8
Requires-Dist: checksum_helper<0.3,>=0.2.4
Provides-Extra: test
Requires-Dist: pytest<8,>=7.2; extra == "test"
